pyexvalid/__init__.py
pyexvalid/calibration_plot.py
pyexvalid/logistic_model.py
pyexvalid/multiple_imputation.py
pyexvalid/performance_metrics.py
pyexvalid-0.1.1.dist-info/licenses/LICENSE
pyexvalid-0.1.1.dist-info/METADATA
pyexvalid-0.1.1.dist-info/WHEEL
pyexvalid-0.1.1.dist-info/top_level.txt
pyexvalid-0.1.1.dist-info/RECORD
